README.md
setup.py
moqu/__init__.py
moqu.egg-info/PKG-INFO
moqu.egg-info/SOURCES.txt
moqu.egg-info/dependency_links.txt
moqu.egg-info/top_level.txt