Metadata-Version: 1.0
Name: moqu
Version: 0.1.0
Summary: moqu
Home-page: https://github.com/Necior/moqu
Author: Adrian Sadłocha
Author-email: UNKNOWN
License: UNKNOWN
Platform: UNKNOWN
